critical_path/__init__.py
critical_path/BERT/__init__.py
critical_path/BERT/configs.py
critical_path/BERT/model_classifier.py
critical_path/BERT/model_multilabel_class.py
critical_path/BERT/model_squad.py
critical_path/BERT/modeling.py
critical_path/BERT/optimization.py
critical_path/BERT/tokenization.py
critical_path-0.0.9.dist-info/LICENSE
critical_path-0.0.9.dist-info/METADATA
critical_path-0.0.9.dist-info/WHEEL
critical_path-0.0.9.dist-info/top_level.txt
critical_path-0.0.9.dist-info/RECORD
