Metadata-Version: 2.1
Name: critical-path
Version: 0.0.9
Summary: Tools for adapting universal language models to specifc tasks
Home-page: https://github.com/ltskinner/critical-path-nlp
Author: ltskinner
License: Apache
Keywords: BERT google transformer squad SQuAD nlp
Platform: UNKNOWN
Requires-Dist: tensorflow
